README.txt
setup.py
collective/__init__.py
collective.twitter.action.egg-info/PKG-INFO
collective.twitter.action.egg-info/SOURCES.txt
collective.twitter.action.egg-info/dependency_links.txt
collective.twitter.action.egg-info/entry_points.txt
collective.twitter.action.egg-info/namespace_packages.txt
collective.twitter.action.egg-info/not-zip-safe
collective.twitter.action.egg-info/requires.txt
collective.twitter.action.egg-info/top_level.txt
collective/twitter/__init__.py
collective/twitter/action/__init__.py
collective/twitter/action/configure.zcml
collective/twitter/action/twitter_action.py
collective/twitter/action/locales/collective.twitter.action.pot
collective/twitter/action/locales/es/LC_MESSAGES/collective.twitter.action.mo
collective/twitter/action/locales/es/LC_MESSAGES/collective.twitter.action.po
docs/HISTORY.txt
docs/INSTALL.txt
docs/LICENSE.GPL
docs/LICENSE.txt