Metadata-Version: 1.0
Name: collective.twitter.action
Version: 1.0.1
Summary: Content rules action to post on Twitter
Home-page: http://svn.plone.org/svn/collective/collective.twitter.action
Author: Franco Pellegrini
Author-email: frapell@menttes.com
License: GPL
Platform: UNKNOWN
Classifier: Framework :: Plone
Classifier: Programming Language :: Python
